pypwsqc/__init__.py
pypwsqc/flagging.py
pypwsqc/indicator_correlation.py
pypwsqc/peak_removal_filter.py
pypwsqc/peak_removal_filter_plots.py
pypwsqc/py.typed
pypwsqc-0.2.1.dist-info/LICENSE
pypwsqc-0.2.1.dist-info/METADATA
pypwsqc-0.2.1.dist-info/WHEEL
pypwsqc-0.2.1.dist-info/RECORD
